LICENSE
README.md
setup.py
docs/__init__.py
richard/__init__.py
richard.egg-info/PKG-INFO
richard.egg-info/SOURCES.txt
richard.egg-info/dependency_links.txt
richard.egg-info/top_level.txt
richard/block/FindAll.py
richard/block/FindOne.py
richard/block/Succeed.py
richard/block/TryFirst.py
richard/block/__init__.py
richard/core/DialogTester.py
richard/core/Logger.py
richard/core/Model.py
richard/core/Pipeline.py
richard/core/Solver.py
richard/core/__init__.py
richard/core/atoms.py
richard/core/constants.py
richard/data_source/MemoryDbDataSource.py
richard/data_source/MySqlDataSource.py
richard/data_source/PsycoPg2DataSource.py
richard/data_source/PsycoPg3DataSource.py
richard/data_source/SparqlDataSource.py
richard/data_source/Sqlite3DataSource.py
richard/data_source/WikidataDataSource.py
richard/data_source/__init__.py
richard/entity/BlockResult.py
richard/entity/ControlBlock.py
richard/entity/GrammarRule.py
richard/entity/GrammarRules.py
richard/entity/ParseTreeNode.py
richard/entity/ProcessResult.py
richard/entity/ProcessingException.py
richard/entity/ReifiedVariable.py
richard/entity/Relation.py
richard/entity/RuleConstituent.py
richard/entity/SentenceRequest.py
richard/entity/Variable.py
richard/entity/__init__.py
richard/interface/Product.py
richard/interface/SomeClearableDb.py
richard/interface/SomeDataSource.py
richard/interface/SomeLogger.py
richard/interface/SomeModule.py
richard/interface/SomeParseTreeSortHeuristics.py
richard/interface/SomeProcessor.py
richard/interface/SomeQueryOptimizer.py
richard/interface/SomeResponseHandler.py
richard/interface/SomeSolver.py
richard/interface/__init__.py
richard/module/BasicSentenceContext.py
richard/module/CoreModule.py
richard/module/InferenceModule.py
richard/module/SimpleMemoryModule.py
richard/module/__init__.py
richard/module/helper/SimpleInferenceRuleParser.py
richard/module/helper/__init__.py
richard/processor/__init__.py
richard/processor/language_selector/LanguageSelector.py
richard/processor/language_selector/LanguageSelectorProduct.py
richard/processor/language_selector/Multilingual.py
